mkdocs_protobuf/__init__.py
mkdocs_protobuf/plugin.py
mkdocs_protobuf-0.1.0.dist-info/LICENSE
mkdocs_protobuf-0.1.0.dist-info/METADATA
mkdocs_protobuf-0.1.0.dist-info/WHEEL
mkdocs_protobuf-0.1.0.dist-info/entry_points.txt
mkdocs_protobuf-0.1.0.dist-info/top_level.txt
mkdocs_protobuf-0.1.0.dist-info/RECORD
