Metadata-Version: 2.1
Name: mkdocs-protobuf
Version: 0.1.0
Summary: Mkdocs plugin to render protobuf messages
Home-page: https://github.com/rymurr/mkdocs-protobuf
Author: Ryan Murray
Author-email: rymurr@gmail.com
License: Apache Software License 2.0
Keywords: mkdocs_protobuf,mkdocs,protobuf
Platform: UNKNOWN
Classifier: Programming Language :: Python :: 3.6
Classifier: Programming Language :: Python :: 3.7
Classifier: Programming Language :: Python :: 3.8
Classifier: Programming Language :: Python :: 3.9
Classifier: Programming Language :: Python :: 3 :: Only
Requires-Python: >=3.6
